uvtools/GIT_INFO
uvtools/VERSION
uvtools/__init__.py
uvtools/binning.py
uvtools/dspec.py
uvtools/fringe.py
uvtools/notebook.py
uvtools/pfb.py
uvtools/plot.py
uvtools/pspec.py
uvtools/utils.py
uvtools/version.py
uvtools/data/__init__.py
uvtools/data/noiselike_eor_diff.uvh5
uvtools/data/simulated_eor.uvh5
uvtools/data/uvd1.uvh5
uvtools/data/uvd2.uvh5
uvtools/data/uvd_1d_freqs.uvh5
uvtools/data/uvd_1d_times.uvh5
uvtools/data/uvd_1d_uvws.uvh5
uvtools/data/uvd_bad_Nfreq.uvh5
uvtools/data/uvd_bad_Ntimes.uvh5
uvtools/data/uvd_bad_ants.uvh5
uvtools/data/uvd_bad_bls.uvh5
uvtools/data/uvd_bad_chan_width.uvh5
uvtools/data/uvd_bad_int_time.uvh5
uvtools/data/zen.2458042.17772.xx.HH.uvXA/flags
uvtools/data/zen.2458042.17772.xx.HH.uvXA/header
uvtools/data/zen.2458042.17772.xx.HH.uvXA/history
uvtools/data/zen.2458042.17772.xx.HH.uvXA/vartable
uvtools/data/zen.2458042.17772.xx.HH.uvXA/visdata
uvtools/data/zen.all.xx.LST.1.06964.uvA/flags
uvtools/data/zen.all.xx.LST.1.06964.uvA/header
uvtools/data/zen.all.xx.LST.1.06964.uvA/history
uvtools/data/zen.all.xx.LST.1.06964.uvA/vartable
uvtools/data/zen.all.xx.LST.1.06964.uvA/visdata
uvtools/tests/__init__.py
uvtools/tests/test_dspec.py
uvtools/tests/test_plot.py
uvtools/tests/test_utils.py
uvtools-0.1.0.data/scripts/plot_uv.py
uvtools-0.1.0.data/scripts/uvtools_print_corr_metric.py
uvtools-0.1.0.data/scripts/uvtools_print_data.py
uvtools-0.1.0.data/scripts/uvtools_print_metadata.py
uvtools-0.1.0.dist-info/LICENSE
uvtools-0.1.0.dist-info/METADATA
uvtools-0.1.0.dist-info/WHEEL
uvtools-0.1.0.dist-info/top_level.txt
uvtools-0.1.0.dist-info/RECORD
