Metadata-Version: 2.1
Name: uvtools
Version: 0.1.0
Summary: Tools useful for the handling, visualization, and analysis of interferometric data.
Home-page: https://github.com/HERA-Team/uvtools
Author: HERA Team
License: BSD
Platform: UNKNOWN
License-File: LICENSE
Requires-Dist: numpy
Requires-Dist: six
Requires-Dist: scipy
Provides-Extra: aipy
Requires-Dist: aipy (>=3.0rc2) ; extra == 'aipy'
